duguidlab_signal_separation-2.0.dev0.dist-info/licenses/LICENSE
fissa/__init__.py
fissa/__meta__.py
fissa/core.py
fissa/deltaf.py
fissa/extraction.py
fissa/neuropil.py
fissa/polygons.py
fissa/readimagejrois.py
fissa/roitools.py
duguidlab_signal_separation-2.0.dev0.dist-info/METADATA
duguidlab_signal_separation-2.0.dev0.dist-info/WHEEL
duguidlab_signal_separation-2.0.dev0.dist-info/top_level.txt
duguidlab_signal_separation-2.0.dev0.dist-info/RECORD
